{"entity":{"id":"recdAEKHh1UTSldTD","type":"chapter","slug":"recdAEKHh1UTSldTD","label":"Job.26","rawId":"recdAEKHh1UTSldTD","book":{"id":"recOA8nVVhKs30PSI","type":"book","slug":"job","label":"Job","subtitle":"Poetry-Wisdom","count":1070,"description":"42 chapters, 190 people, 6 places"}},"stats":{"verses":14,"people":1,"places":0,"events":1},"nodes":[{"id":"recdAEKHh1UTSldTD","type":"chapter","group":"focus","label":"Job.26","slug":"job_26","score":14,"description":""},{"id":"recOA8nVVhKs30PSI","type":"book","group":"book","label":"Job","slug":"job","score":1070,"description":"42 chapters, 190 people, 6 places"},{"id":"recKXL1QrW8qTw5Ux","type":"person","group":"mentioned","label":"Job","slug":"job_1639","score":1,"description":"Persecuted, an Arabian patriarch who resided in the land of Uz (q.v.). While living in the midst of great prosperity, he was suddenly overwhelmed by a series of sore trials that fell upon him. Amid all his sufferings he maintained his integrity. Once more God visited him with the rich tokens of his goodness and even greater prosperity than he had enjoyed before. He survived the period of trial for one hundred and forty years, and died in a good old age, an example to succeeding generations of integrity (Ezek. 14:14, 20) and of submissive patience under the sorest calamities (James 5:11). His history, so far as it is known, is recorded in his book."},{"id":"recMNT9RB1RJiLlYW","type":"event","group":"event","label":"Job's Trial","slug":"event-117","score":14,"description":""}],"links":[{"source":"recdAEKHh1UTSldTD","target":"recOA8nVVhKs30PSI","label":"part of"},{"source":"recdAEKHh1UTSldTD","target":"recKXL1QrW8qTw5Ux","label":"mentions"},{"source":"recdAEKHh1UTSldTD","target":"recMNT9RB1RJiLlYW","label":"event"}],"verses":[{"id":"recLFMgDv8e0RTGNs","ref":"Job.26.1","text":"But Job answered and said,","year":-1520},{"id":"recE9B7ZZQSYxrSI3","ref":"Job.26.2","text":"How hast thou helped him that is without power? how savest thou the arm that hath no strength?","year":-1520},{"id":"recNNLxjocPhOJnMi","ref":"Job.26.3","text":"How hast thou counselled him that hath no wisdom? and how hast thou plentifully declared the thing as it is?","year":-1520},{"id":"recZOS4tYmaSinUVI","ref":"Job.26.4","text":"To whom hast thou uttered words? and whose spirit came from thee?","year":-1520},{"id":"rec1JVyTqtNjuFSuH","ref":"Job.26.5","text":"Dead things are formed from under the waters, and the inhabitants thereof.","year":-1520},{"id":"recAbdo87AFFAgnaw","ref":"Job.26.6","text":"Hell is naked before him, and destruction hath no covering.","year":-1520},{"id":"rec6CvB88MeaS3IdH","ref":"Job.26.7","text":"He stretcheth out the north over the empty place, and hangeth the earth upon nothing.","year":-1520},{"id":"recyC34mNh0cWvhUE","ref":"Job.26.8","text":"He bindeth up the waters in his thick clouds; and the cloud is not rent under them.","year":-1520}]}
