{"entity":{"id":"recRP17BhOpl9Q6pE","type":"chapter","slug":"recRP17BhOpl9Q6pE","label":"Ps.37","rawId":"recRP17BhOpl9Q6pE","book":{"id":"recKXZXO6cJwk2SxO","type":"book","slug":"ps","label":"Psalms","subtitle":"Poetry-Wisdom","count":2461,"description":"150 chapters, 1026 people, 118 places"}},"stats":{"verses":40,"people":1,"places":0,"events":0},"nodes":[{"id":"recRP17BhOpl9Q6pE","type":"chapter","group":"focus","label":"Ps.37","slug":"ps_37","score":40},{"id":"recKXZXO6cJwk2SxO","type":"book","group":"book","label":"Psalms","slug":"ps","score":2461},{"id":"reccZB8SVU5bEMcgo","type":"person","group":"mentioned","label":"God","slug":"god_1324","score":17}],"links":[{"source":"recRP17BhOpl9Q6pE","target":"recKXZXO6cJwk2SxO","label":"part of"},{"source":"recRP17BhOpl9Q6pE","target":"reccZB8SVU5bEMcgo","label":"mentions"}],"verses":[{"id":"recXVqVOZbVPAEO7V","ref":"Ps.37.1","text":"Fret not thyself because of evildoers, neither be thou envious against the workers of iniquity."},{"id":"recHh3Zee7s1apGij","ref":"Ps.37.2","text":"For they shall soon be cut down like the grass, and wither as the green herb."},{"id":"recEiLg1wbY3Oitqv","ref":"Ps.37.3","text":"Trust in the LORD, and do good; so shalt thou dwell in the land, and verily thou shalt be fed."},{"id":"recTe9SPdBXdD2a92","ref":"Ps.37.4","text":"Delight thyself also in the LORD; and he shall give thee the desires of thine heart."},{"id":"recEgDc9PvW2HXVB6","ref":"Ps.37.5","text":"Commit thy way unto the LORD; trust also in him; and he shall bring it to pass."},{"id":"reczfnUgpfQkw6QDt","ref":"Ps.37.6","text":"And he shall bring forth thy righteousness as the light, and thy judgment as the noonday."},{"id":"recuf19ByNkngoMLQ","ref":"Ps.37.7","text":"Rest in the LORD, and wait patiently for him: fret not thyself because of him who prospereth in his way, because of the man who bringeth wicked devices to pass."},{"id":"recoJWoOa3RW3F9JV","ref":"Ps.37.8","text":"Cease from anger, and forsake wrath: fret not thyself in any wise to do evil."}]}
