{"entity":{"id":"recQ8DF0pj7A20FyQ","type":"place","slug":"chesulloth_290","label":"Chesulloth","subtitle":"City","count":1,"lat":32.683231,"lon":35.324694,"description":"Fertile places; the loins, a town of Issachar, on the slopes of some mountain between Jezreel and Shunem (Josh. 19:18). It has been identified with Chisloth-tabor, 2 1/2 miles to the west of Mount Tabor, and north of Jezreel; now Iksal.","rawId":"recQ8DF0pj7A20FyQ"},"stats":{"verses":1,"events":0,"people":0},"nodes":[{"id":"recQ8DF0pj7A20FyQ","type":"place","group":"focus","label":"Chesulloth","slug":"chesulloth_290","score":1,"description":"Fertile places; the loins, a town of Issachar, on the slopes of some mountain between Jezreel and Shunem (Josh. 19:18). It has been identified with Chisloth-tabor, 2 1/2 miles to the west of Mount Tabor, and north of Jezreel; now Iksal."}],"links":[],"verses":[{"id":"recWZGkOHlq15C2PD","ref":"Josh.19.18","text":"And their border was toward Jezreel, and Chesulloth, and Shunem,","year":-1443}],"allRefs":["Josh.19.18"]}
