{"entity":{"id":"recTSS22B5fmom2Vh","type":"place","slug":"gebim_450","label":"Gebim","subtitle":"Place","count":1,"lat":31.8,"lon":35.25,"description":"Cisterns, (rendered “pits,” Jer. 14:3; “locusts,” Isa. 33:4), a small place north of Jerusalem, whose inhabitants fled at the approach of the Assyrian army (Isa. 10:31). It is probably the modern el-Isawiyeh.","rawId":"recTSS22B5fmom2Vh"},"stats":{"verses":1,"events":0,"people":0},"nodes":[{"id":"recTSS22B5fmom2Vh","type":"place","group":"focus","label":"Gebim","slug":"gebim_450","score":1,"description":"Cisterns, (rendered “pits,” Jer. 14:3; “locusts,” Isa. 33:4), a small place north of Jerusalem, whose inhabitants fled at the approach of the Assyrian army (Isa. 10:31). It is probably the modern el-Isawiyeh."}],"links":[],"verses":[{"id":"recmrtF4e7QxL3rD4","ref":"Isa.10.31","text":"Madmenah is removed; the inhabitants of Gebim gather themselves to flee.","year":-713}],"allRefs":["Isa.10.31"]}
