{"entity":{"id":"recY6LiTKJcRArcz0","type":"place","slug":"mizpeh_813","label":"Mizpeh","subtitle":"Place","count":1,"lat":31.56485056116292,"lon":34.8467256730566,"description":"","rawId":"recY6LiTKJcRArcz0"},"stats":{"verses":1,"events":0,"people":0},"nodes":[{"id":"recY6LiTKJcRArcz0","type":"place","group":"focus","label":"Mizpeh","slug":"mizpeh_813","score":1,"description":""}],"links":[],"verses":[{"id":"recetb7QXr4biYGmR","ref":"Josh.15.38","text":"And Dilean, and Mizpeh, and Joktheel,","year":-1443}],"allRefs":["Josh.15.38"]}
