{"entity":{"id":"recgg7kwUkrmxzV6Z","type":"place","slug":"ophni_912","label":"Ophni","subtitle":"City","count":1,"lat":31.961989,"lon":35.215483,"description":"Mouldy, a city of Benjamin (Josh. 18:24).","rawId":"recgg7kwUkrmxzV6Z"},"stats":{"verses":1,"events":0,"people":0},"nodes":[{"id":"recgg7kwUkrmxzV6Z","type":"place","group":"focus","label":"Ophni","slug":"ophni_912","score":1,"description":"Mouldy, a city of Benjamin (Josh. 18:24)."}],"links":[],"verses":[{"id":"recdx5YS6pnZ8Mr8F","ref":"Josh.18.24","text":"And Chepharhaammonai, and Ophni, and Gaba; twelve cities with their villages:","year":-1443}],"allRefs":["Josh.18.24"]}
