{"entity":{"id":"recC86IzmexcQRTDL","type":"place","slug":"salt_302","label":"Salt","subtitle":"City","count":1,"lat":31.46152536164766,"lon":35.39241108242345,"description":"One of the cities of Judah (Josh. 15:62), probably in the Valley of Salt, at the southern end of the Dead Sea.","rawId":"recC86IzmexcQRTDL"},"stats":{"verses":1,"events":0,"people":0},"nodes":[{"id":"recC86IzmexcQRTDL","type":"place","group":"focus","label":"Salt","slug":"salt_302","score":1,"description":"One of the cities of Judah (Josh. 15:62), probably in the Valley of Salt, at the southern end of the Dead Sea."}],"links":[],"verses":[{"id":"rec0rWXSsB5L3lD3D","ref":"Josh.15.62","text":"And Nibshan, and the city of Salt, and Engedi; six cities with their villages.","year":-1443}],"allRefs":["Josh.15.62"]}
