{"entity":{"id":"recCZdm8vPvnjEex5","type":"place","slug":"tabor_1129","label":"Tabor (town)","subtitle":"City","count":1,"lat":32.683231,"lon":35.324694,"description":"A town of Zebulum (1 Chr. 6:77).","rawId":"recCZdm8vPvnjEex5"},"stats":{"verses":1,"events":0,"people":0},"nodes":[{"id":"recCZdm8vPvnjEex5","type":"place","group":"focus","label":"Tabor (town)","slug":"tabor_1129","score":1,"description":"A town of Zebulum (1 Chr. 6:77)."}],"links":[],"verses":[{"id":"recA66FL2lDXhfUpx","ref":"1Chr.6.77","text":"Unto the rest of the children of Merari were given out of the tribe of Zebulun, Rimmon with her suburbs, Tabor with her suburbs:","year":-1443}],"allRefs":["1Chr.6.77"]}
