{"entity":{"id":"recmitDCfzrDlCc2P","type":"place","slug":"zereth-shahar_1257","label":"Zereth-shahar","subtitle":"Place","count":1,"lat":31.616962,"lon":35.567522,"description":"","rawId":"recmitDCfzrDlCc2P"},"stats":{"verses":1,"events":0,"people":0},"nodes":[{"id":"recmitDCfzrDlCc2P","type":"place","group":"focus","label":"Zereth-shahar","slug":"zereth-shahar_1257","score":1,"description":""}],"links":[],"verses":[{"id":"recqKFjss3WfdY2aB","ref":"Josh.13.19","text":"And Kirjathaim, and Sibmah, and Zarethshahar in the mount of the valley,","year":-1444}],"allRefs":["Josh.13.19"]}
