{"entity":{"id":"rec8PUlnPsEnCHu4s","type":"place","slug":"ziph_1267","label":"Ziph","subtitle":"City","count":1,"lat":31.162327,"lon":35.057114,"description":"A city in the south of Judah (Josh. 15:24), probably at the pass of Sufah.","rawId":"rec8PUlnPsEnCHu4s"},"stats":{"verses":1,"events":0,"people":0},"nodes":[{"id":"rec8PUlnPsEnCHu4s","type":"place","group":"focus","label":"Ziph","slug":"ziph_1267","score":1,"description":"A city in the south of Judah (Josh. 15:24), probably at the pass of Sufah."}],"links":[],"verses":[{"id":"rec5sr4ssyvexr1oQ","ref":"Josh.15.24","text":"Ziph, and Telem, and Bealoth,","year":-1443}],"allRefs":["Josh.15.24"]}
