{"entity":{"id":"recd4mOzI2nL66vR5","type":"event","slug":"event-85","label":"Birth of Jacob and Esau","subtitle":"1836 BC","count":3,"description":"","rawId":"recd4mOzI2nL66vR5"},"stats":{"verses":3,"participants":4,"locations":0},"nodes":[{"id":"recd4mOzI2nL66vR5","type":"event","group":"focus","label":"Birth of Jacob and Esau","slug":"event-85","score":3},{"id":"recUQWSZuOecG4z1Q","type":"person","group":"person","label":"Esau (Edom)","slug":"esau_1216","score":151},{"id":"recsU2ZSdzBvDqzgI","type":"person","group":"person","label":"Jacob (Israel)","slug":"israel_682","score":1009},{"id":"recZb9e7YIG9qh2qX","type":"person","group":"person","label":"Rebekah","slug":"rebekah_2401","score":29},{"id":"recqIoG1fkaNWJ1y0","type":"person","group":"person","label":"Isaac","slug":"isaac_616","score":123},{"id":"recTkocSMI0NxpIrw","type":"event","group":"event","label":"Lifetime of Jacob","slug":"event-86","score":5}],"links":[{"source":"recd4mOzI2nL66vR5","target":"recUQWSZuOecG4z1Q","label":"participant"},{"source":"recd4mOzI2nL66vR5","target":"recsU2ZSdzBvDqzgI","label":"participant"},{"source":"recd4mOzI2nL66vR5","target":"recZb9e7YIG9qh2qX","label":"participant"},{"source":"recd4mOzI2nL66vR5","target":"recqIoG1fkaNWJ1y0","label":"participant"},{"source":"recd4mOzI2nL66vR5","target":"recTkocSMI0NxpIrw","label":"part of"}],"verses":[{"id":"recqg3HN6jy8k4vT0","ref":"Gen.25.25","text":"And the first came out red, all over like an hairy garment; and they called his name Esau.","year":-1836},{"id":"recCw0IUCy0TfKTkS","ref":"Gen.25.24","text":"And when her days to be delivered were fulfilled, behold, there were twins in her womb.","year":-1836},{"id":"recF0awhZCSb06TMf","ref":"Gen.25.26","text":"And after that came his brother out, and his hand took hold on Esau’s heel; and his name was called Jacob: and Isaac was threescore years old when she bare them.","year":-1836}]}
