{"entity":{"id":"rec8BApZ81SUEiaE6","type":"event","slug":"event-92","label":"Birth of Simeon","subtitle":"1757 BC","count":1,"description":"","rawId":"rec8BApZ81SUEiaE6"},"stats":{"verses":1,"participants":3,"locations":0},"nodes":[{"id":"rec8BApZ81SUEiaE6","type":"event","group":"focus","label":"Birth of Simeon","slug":"event-92","score":1},{"id":"recjDsafRYaksAqa1","type":"person","group":"person","label":"Simeon","slug":"simeon_2741","score":40},{"id":"recsU2ZSdzBvDqzgI","type":"person","group":"person","label":"Jacob (Israel)","slug":"israel_682","score":1009},{"id":"recCLJAZbd4JtoMv6","type":"person","group":"person","label":"Leah","slug":"leah_1813","score":32}],"links":[{"source":"rec8BApZ81SUEiaE6","target":"recjDsafRYaksAqa1","label":"participant"},{"source":"rec8BApZ81SUEiaE6","target":"recsU2ZSdzBvDqzgI","label":"participant"},{"source":"rec8BApZ81SUEiaE6","target":"recCLJAZbd4JtoMv6","label":"participant"}],"verses":[{"id":"rec0EyYCkQqHraNMA","ref":"Gen.29.33","text":"And she conceived again, and bare a son; and said, Because the LORD hath heard that I was hated, he hath therefore given me this son also: and she called his name Simeon.","year":-1751}]}
