{"entity":{"id":"recs1VxMp6PJ11GLW","type":"event","slug":"event-431","label":"Feast of Dedication","subtitle":"0029-12-17","count":18,"description":"Kislev 25, Mon Dec 17th 29 AD","rawId":"recs1VxMp6PJ11GLW"},"stats":{"verses":18,"participants":1,"locations":1},"nodes":[{"id":"recs1VxMp6PJ11GLW","type":"event","group":"focus","label":"Feast of Dedication","slug":"event-431","score":18},{"id":"recgkFqZovgbr3pAi","type":"person","group":"person","label":"Jesus Christ","slug":"jesus_905","score":1831},{"id":"recL1WV82pXaRBQ59","type":"place","group":"place","label":"Jerusalem","slug":"jerusalem_636","score":754},{"id":"recoUkvcVV6nR1G2D","type":"event","group":"event","label":"Mustard Seed and Leaven Teaching","slug":"event-430","score":5}],"links":[{"source":"recs1VxMp6PJ11GLW","target":"recgkFqZovgbr3pAi","label":"participant"},{"source":"recs1VxMp6PJ11GLW","target":"recL1WV82pXaRBQ59","label":"location"},{"source":"recs1VxMp6PJ11GLW","target":"recoUkvcVV6nR1G2D","label":"predecessor"}],"verses":[{"id":"recQn7vJS6l8BXPfe","ref":"John.10.22","text":"And it was at Jerusalem the feast of the dedication, and it was winter.","year":33},{"id":"recDTHLHBIC6AOc1L","ref":"John.10.23","text":"And Jesus walked in the temple in Solomon’s porch.","year":33},{"id":"rec5wAAteDTnGjsdW","ref":"John.10.24","text":"Then came the Jews round about him, and said unto him, How long dost thou make us to doubt? If thou be the Christ, tell us plainly.","year":33},{"id":"rec0bFTiuwE0pdTPl","ref":"John.10.25","text":"Jesus answered them, I told you, and ye believed not: the works that I do in my Father’s name, they bear witness of me.","year":33},{"id":"recUkvaSbW23Fv2vr","ref":"John.10.26","text":"But ye believe not, because ye are not of my sheep, as I said unto you.","year":33},{"id":"rec37Ujhau53CH2FO","ref":"John.10.27","text":"My sheep hear my voice, and I know them, and they follow me:","year":33},{"id":"recr5X01veGbHe8DO","ref":"John.10.28","text":"And I give unto them eternal life; and they shall never perish, neither shall any man pluck them out of my hand.","year":33},{"id":"rec6jirWychLlo9GE","ref":"John.10.29","text":"My Father, which gave them me, is greater than all; and no man is able to pluck them out of my Father’s hand.","year":33}]}
