{"entity":{"id":"reclZp6jMKWzYmop9","type":"event","slug":"event-433","label":"Lazarus Raised form the Dead","subtitle":"AD 30","count":46,"description":"","rawId":"reclZp6jMKWzYmop9"},"stats":{"verses":46,"participants":3,"locations":1},"nodes":[{"id":"reclZp6jMKWzYmop9","type":"event","group":"focus","label":"Lazarus Raised form the Dead","slug":"event-433","score":46},{"id":"recgkFqZovgbr3pAi","type":"person","group":"person","label":"Jesus Christ","slug":"jesus_905","score":1831},{"id":"recEKfDWYNYOUAUVH","type":"person","group":"person","label":"Mary (sister of Lazarus)","slug":"mary_1939","score":11},{"id":"recy6ANqZT7KobHD2","type":"person","group":"person","label":"Lazarus","slug":"lazarus_1812","score":11},{"id":"recLDF53uVzhhlyux","type":"place","group":"place","label":"Bethany","slug":"bethany_186","score":11},{"id":"rec70ZLu9pdrEWXR9","type":"event","group":"event","label":"Teaching and Healing in Perea to Jerusalem","slug":"event-432","score":5}],"links":[{"source":"reclZp6jMKWzYmop9","target":"recgkFqZovgbr3pAi","label":"participant"},{"source":"reclZp6jMKWzYmop9","target":"recEKfDWYNYOUAUVH","label":"participant"},{"source":"reclZp6jMKWzYmop9","target":"recy6ANqZT7KobHD2","label":"participant"},{"source":"reclZp6jMKWzYmop9","target":"recLDF53uVzhhlyux","label":"location"},{"source":"reclZp6jMKWzYmop9","target":"rec70ZLu9pdrEWXR9","label":"predecessor"}],"verses":[{"id":"recPvzgjtZnhRsjtD","ref":"John.11.1","text":"Now a certain man was sick, named Lazarus, of Bethany, the town of Mary and her sister Martha.","year":33},{"id":"recesFbSIR3bDDVzC","ref":"John.11.2","text":"It was that Mary which anointed the Lord with ointment, and wiped his feet with her hair, whose brother Lazarus was sick.)","year":33},{"id":"recABjZmmbftMeYnh","ref":"John.11.3","text":"Therefore his sisters sent unto him, saying, Lord, behold, he whom thou lovest is sick.","year":33},{"id":"recdfucFPhoSWhQcX","ref":"John.11.4","text":"When Jesus heard that, he said, This sickness is not unto death, but for the glory of God, that the Son of God might be glorified thereby.","year":33},{"id":"rechR22pxCYnnqnUD","ref":"John.11.5","text":"Now Jesus loved Martha, and her sister, and Lazarus.","year":33},{"id":"reci1YVHCOtNHGF27","ref":"John.11.6","text":"When he had heard therefore that he was sick, he abode two days still in the same place where he was.","year":33},{"id":"recCdyaOokVCPJJc3","ref":"John.11.7","text":"Then after that saith he to his disciples, Let us go into Judaea again.","year":33},{"id":"recbgfHtGMfx8m30z","ref":"John.11.8","text":"His disciples say unto him, Master, the Jews of late sought to stone thee; and goest thou thither again?","year":33}]}
