{"entity":{"id":"recynRwNAbtX5ShQ7","type":"event","slug":"event-123","label":"Birth of Caleb","subtitle":"1529 BC","count":1,"description":"","rawId":"recynRwNAbtX5ShQ7"},"stats":{"verses":1,"participants":1,"locations":0},"nodes":[{"id":"recynRwNAbtX5ShQ7","type":"event","group":"focus","label":"Birth of Caleb","slug":"event-123","score":1},{"id":"recVua5TkKSl3y6Ol","type":"person","group":"person","label":"Caleb","slug":"caleb_537","score":30}],"links":[{"source":"recynRwNAbtX5ShQ7","target":"recVua5TkKSl3y6Ol","label":"participant"}],"verses":[{"id":"recWyWTjIkszdZ0Xm","ref":"Num.13.6","text":"Of the tribe of Judah, Caleb the son of Jephunneh.","year":-1490}]}
