{"entity":{"id":"recL1uy0J3IByZrPM","type":"person","slug":"azur_569","label":"Azur","subtitle":"Male","count":1,"years":"Unknown - Unknown","description":"The father of Hananiah, a false prophet (Jer. 28:1).","rawId":"recL1uy0J3IByZrPM"},"stats":{"verses":1,"events":0,"family":1},"nodes":[{"id":"recL1uy0J3IByZrPM","type":"person","group":"focus","label":"Azur","slug":"azur_569","score":1,"description":"The father of Hananiah, a false prophet (Jer. 28:1)."},{"id":"recRexfzjGS7kUEIQ","type":"person","group":"children","label":"Hananiah","slug":"hananiah_1395","score":8,"description":""}],"links":[{"source":"recL1uy0J3IByZrPM","target":"recRexfzjGS7kUEIQ","label":"children"}],"verses":[{"id":"rec5FjblKCLOkDhA9","ref":"Jer.28.1","text":"And it came to pass the same year, in the beginning of the reign of Zedekiah king of Judah, in the fourth year, and in the fifth month, that Hananiah the son of Azur the prophet, which was of Gibeon, spake unto me in the house of the LORD, in the presence of the priests and of all the people, saying,","year":-595}],"allRefs":["Jer.28.1"]}
