{"entity":{"id":"rec1S4nN14Yk7klhb","type":"person","slug":"bered_476","label":"Bered","subtitle":"Male","count":1,"years":"Unknown - Unknown","description":"A son of Shuthelah, and grandson of Ephraim (1 Chr. 7:20).","rawId":"rec1S4nN14Yk7klhb"},"stats":{"verses":1,"events":0,"family":3},"nodes":[{"id":"rec1S4nN14Yk7klhb","type":"person","group":"focus","label":"Bered","slug":"bered_476","score":1,"description":"A son of Shuthelah, and grandson of Ephraim (1 Chr. 7:20)."},{"id":"recGllq2rdoUh8LJD","type":"person","group":"father","label":"Shuthelah","slug":"shuthelah_2734","score":3,"description":""},{"id":"rec08Kd5j4fUsF1na","type":"person","group":"children","label":"Tahath","slug":"tahath_2815","score":1,"description":""},{"id":"recBGM7FM6ZLFt91b","type":"person","group":"siblings","label":"Eran","slug":"eran_1212","score":1,"description":""}],"links":[{"source":"rec1S4nN14Yk7klhb","target":"recGllq2rdoUh8LJD","label":"father"},{"source":"rec1S4nN14Yk7klhb","target":"rec08Kd5j4fUsF1na","label":"children"},{"source":"rec1S4nN14Yk7klhb","target":"recBGM7FM6ZLFt91b","label":"siblings"}],"verses":[{"id":"reccG070q0pXxvtEE","ref":"1Chr.7.20","text":"And the sons of Ephraim; Shuthelah, and Bered his son, and Tahath his son, and Eladah his son, and Tahath his son,"}],"allRefs":["1Chr.7.20"]}
