{"entity":{"id":"recvU6R8BjnTVYM3Q","type":"person","slug":"binnui_508","label":"Binnui","subtitle":"Male","count":1,"years":"Unknown - Unknown","description":"","rawId":"recvU6R8BjnTVYM3Q"},"stats":{"verses":1,"events":0,"family":1},"nodes":[{"id":"recvU6R8BjnTVYM3Q","type":"person","group":"focus","label":"Binnui","slug":"binnui_508","score":1,"description":""},{"id":"recMv6nOJiEoNZ7zy","type":"person","group":"children","label":"Noadiah","slug":"noadiah_2208","score":1,"description":"A Levite who returned from Babylon (Ezra 8:33)."}],"links":[{"source":"recvU6R8BjnTVYM3Q","target":"recMv6nOJiEoNZ7zy","label":"children"}],"verses":[{"id":"recpNI1vdSwn7xkWD","ref":"Ezra.8.33","text":"Now on the fourth day was the silver and the gold and the vessels weighed in the house of our God by the hand of Meremoth the son of Uriah the priest; and with him was Eleazar the son of Phinehas; and with them was Jozabad the son of Jeshua, and Noadiah the son of Binnui, Levites;","year":-457}],"allRefs":["Ezra.8.33"]}
