{"entity":{"id":"recH7F0FLNtZiiuGJ","type":"person","slug":"elidad_1103","label":"Elidad","subtitle":"Male","count":1,"years":"Unknown - Unknown","description":"Whom God has loved, son of Chislon, and chief of the tribe of Benjamin; one of those who were appointed to divide the Promised Land among the tribes (Num. 34:21).","rawId":"recH7F0FLNtZiiuGJ"},"stats":{"verses":1,"events":0,"family":1},"nodes":[{"id":"recH7F0FLNtZiiuGJ","type":"person","group":"focus","label":"Elidad","slug":"elidad_1103","score":1,"description":"Whom God has loved, son of Chislon, and chief of the tribe of Benjamin; one of those who were appointed to divide the Promised Land among the tribes (Num. 34:21)."},{"id":"rec40gL1pq1nnzQFC","type":"person","group":"father","label":"Chislon","slug":"chislon_942","score":1,"description":""}],"links":[{"source":"recH7F0FLNtZiiuGJ","target":"rec40gL1pq1nnzQFC","label":"father"}],"verses":[{"id":"recUlNZTdG1XJslgU","ref":"Num.34.21","text":"Of the tribe of Benjamin, Elidad the son of Chislon.","year":-1452}],"allRefs":["Num.34.21"]}
