{"entity":{"id":"recO9tzA6SmHx9C3s","type":"person","slug":"harhaiah_1413","label":"Harhaiah","subtitle":"Male","count":1,"years":"Unknown - Unknown","description":"Zeal of Jehovah, (Neh. 3:8) “of the goldsmiths,” one whose son helped to repair the wall of Jerusalem.","rawId":"recO9tzA6SmHx9C3s"},"stats":{"verses":1,"events":0,"family":1},"nodes":[{"id":"recO9tzA6SmHx9C3s","type":"person","group":"focus","label":"Harhaiah","slug":"harhaiah_1413","score":1,"description":"Zeal of Jehovah, (Neh. 3:8) “of the goldsmiths,” one whose son helped to repair the wall of Jerusalem."},{"id":"recomxuB0a3Jdzvae","type":"person","group":"children","label":"Uzziel","slug":"uzziel_2934","score":1,"description":"The son of Harhaiah (Neh. 3:8)."}],"links":[{"source":"recO9tzA6SmHx9C3s","target":"recomxuB0a3Jdzvae","label":"children"}],"verses":[{"id":"recXAbR4aukQP8xU9","ref":"Neh.3.8","text":"Next unto him repaired Uzziel the son of Harhaiah, of the goldsmiths. Next unto him also repaired Hananiah the son of one of the apothecaries, and they fortified Jerusalem unto the broad wall.","year":-445}],"allRefs":["Neh.3.8"]}
