{"entity":{"id":"recdhuAoifNPK9jdP","type":"person","slug":"jehonathan_802","label":"Jehonathan","subtitle":"Male","count":1,"years":"Unknown - Unknown","description":"Neh. 12:18.","rawId":"recdhuAoifNPK9jdP"},"stats":{"verses":1,"events":0,"family":0},"nodes":[{"id":"recdhuAoifNPK9jdP","type":"person","group":"focus","label":"Jehonathan","slug":"jehonathan_802","score":1,"description":"Neh. 12:18."}],"links":[],"verses":[{"id":"recWDNGmEkmN53FQo","ref":"Neh.12.18","text":"Of Bilgah, Shammua; of Shemaiah, Jehonathan;"}],"allRefs":["Neh.12.18"]}
