{"entity":{"id":"recQqloHEWOlcjrKX","type":"person","slug":"jehoshaphat_807","label":"Jehoshaphat","subtitle":"Male","count":1,"years":"Unknown - Unknown","description":"Solomon’s purveyor in Issachar (1 Kings 4:17).","rawId":"recQqloHEWOlcjrKX"},"stats":{"verses":1,"events":0,"family":1},"nodes":[{"id":"recQqloHEWOlcjrKX","type":"person","group":"focus","label":"Jehoshaphat","slug":"jehoshaphat_807","score":1,"description":"Solomon’s purveyor in Issachar (1 Kings 4:17)."},{"id":"rec3iLHHG1ci0Nyas","type":"person","group":"father","label":"Paruah","slug":"paruah_2278","score":1,"description":"Flourishing, the father of Jehoshaphat, appointed to provide monthly supplies for Solomon from the tribe of Issachar (1 Kings 4:17)."}],"links":[{"source":"recQqloHEWOlcjrKX","target":"rec3iLHHG1ci0Nyas","label":"father"}],"verses":[{"id":"recpPZCP9IyExWXAn","ref":"1Kgs.4.17","text":"Jehoshaphat the son of Paruah, in Issachar:","year":-1014}],"allRefs":["1Kgs.4.17"]}
