{"entity":{"id":"recLm6U4xRrpm6cFW","type":"person","slug":"joah_1626","label":"Joah","subtitle":"Male","count":1,"years":"Unknown - Unknown","description":"Son of Joahaz, and “recorder” (q.v.) or keeper of the state archives under King Josiah (2 Chr. 34:8).","rawId":"recLm6U4xRrpm6cFW"},"stats":{"verses":1,"events":0,"family":1},"nodes":[{"id":"recLm6U4xRrpm6cFW","type":"person","group":"focus","label":"Joah","slug":"joah_1626","score":1,"description":"Son of Joahaz, and “recorder” (q.v.) or keeper of the state archives under King Josiah (2 Chr. 34:8)."},{"id":"recBUaoe1WQohjd9E","type":"person","group":"father","label":"Joahaz","slug":"joahaz_1627","score":1,"description":"(2 Chr. 34:8), a contracted form of Jehoahaz (q.v.)."}],"links":[{"source":"recLm6U4xRrpm6cFW","target":"recBUaoe1WQohjd9E","label":"father"}],"verses":[{"id":"recttTmA2fn5EMsiL","ref":"2Chr.34.8","text":"Now in the eighteenth year of his reign, when he had purged the land, and the house, he sent Shaphan the son of Azaliah, and Maaseiah the governor of the city, and Joah the son of Joahaz the recorder, to repair the house of the LORD his God.","year":-624}],"allRefs":["2Chr.34.8"]}
