{"entity":{"id":"recFtmuJvooDZ8tuS","type":"person","slug":"joseph_1717","label":"Joseph","subtitle":"Male","count":1,"years":"Unknown - Unknown","description":"","rawId":"recFtmuJvooDZ8tuS"},"stats":{"verses":1,"events":0,"family":2},"nodes":[{"id":"recFtmuJvooDZ8tuS","type":"person","group":"focus","label":"Joseph","slug":"joseph_1717","score":1,"description":""},{"id":"recEyr5Zh1AmRei8o","type":"person","group":"father","label":"Mattathias","slug":"mattathias_1963","score":1,"description":"The son of Amos, in the genealogy of our Lord (Luke 3:25)."},{"id":"recI7wWTEzcdGh3U9","type":"person","group":"children","label":"Janna","slug":"janna_724","score":1,"description":""}],"links":[{"source":"recFtmuJvooDZ8tuS","target":"recEyr5Zh1AmRei8o","label":"father"},{"source":"recFtmuJvooDZ8tuS","target":"recI7wWTEzcdGh3U9","label":"children"}],"verses":[{"id":"recUa4CPHUvmUiKuz","ref":"Luke.3.24","text":"Which was the son of Matthat, which was the son of Levi, which was the son of Melchi, which was the son of Janna, which was the son of Joseph,","year":26}],"allRefs":["Luke.3.24"]}
