{"entity":{"id":"receOOCNOnHaHsINB","type":"person","slug":"kenaz_1776","label":"Kenaz","subtitle":"Male","count":3,"years":"Unknown - Unknown","description":"","rawId":"receOOCNOnHaHsINB"},"stats":{"verses":3,"events":0,"family":7},"nodes":[{"id":"receOOCNOnHaHsINB","type":"person","group":"focus","label":"Kenaz","slug":"kenaz_1776","score":3,"description":""},{"id":"rec5NX8uW1K4csGEj","type":"person","group":"father","label":"Eliphaz","slug":"eliphaz_1144","score":8,"description":"The son of Esau by his wife Adah, and father of several Edomitish tribes (Gen. 36:4, 10, 11, 16)."},{"id":"recp3sTywycVRJFZt","type":"person","group":"siblings","label":"Amalek","slug":"amalek_197","score":22,"description":"Dweller in a valley, the son of Eliphaz and grandson of Esau (Gen. 36:12; 1 Chr. 1:36); the chief of an Idumean tribe (Gen. 36:16). His mother was a Horite, a tribe whose territory the descendants of Esau had seized."},{"id":"reciDbbigGBXYc63b","type":"person","group":"siblings","label":"Gatam","slug":"gatam_1281","score":3,"description":""},{"id":"reck78wSw5BXkLTC0","type":"person","group":"siblings","label":"Korah","slug":"korah_1794","score":1,"description":""},{"id":"rec0Ctdb2a8sMOozt","type":"person","group":"siblings","label":"Omar","slug":"omar_2242","score":3,"description":"Eloquent, the son of Eliphaz, who was Esau’s eldest son (Gen. 36:11-15)."},{"id":"recDAmjcERkBwkg8Q","type":"person","group":"siblings","label":"Teman","slug":"teman_2838","score":3,"description":""},{"id":"recaDgdGwgUR3ViVq","type":"person","group":"siblings","label":"Zepho","slug":"zepho_3042","score":3,"description":""}],"links":[{"source":"receOOCNOnHaHsINB","target":"rec5NX8uW1K4csGEj","label":"father"},{"source":"receOOCNOnHaHsINB","target":"recp3sTywycVRJFZt","label":"siblings"},{"source":"receOOCNOnHaHsINB","target":"reciDbbigGBXYc63b","label":"siblings"},{"source":"receOOCNOnHaHsINB","target":"reck78wSw5BXkLTC0","label":"siblings"},{"source":"receOOCNOnHaHsINB","target":"rec0Ctdb2a8sMOozt","label":"siblings"},{"source":"receOOCNOnHaHsINB","target":"recDAmjcERkBwkg8Q","label":"siblings"},{"source":"receOOCNOnHaHsINB","target":"recaDgdGwgUR3ViVq","label":"siblings"}],"verses":[{"id":"recJelx2tu0J23pmr","ref":"Gen.36.11","text":"And the sons of Eliphaz were Teman, Omar, Zepho, and Gatam, and Kenaz.","year":-1734},{"id":"reccPnYCaJ5wQHljE","ref":"Gen.36.15","text":"These were dukes of the sons of Esau: the sons of Eliphaz the firstborn son of Esau; duke Teman, duke Omar, duke Zepho, duke Kenaz,","year":-1712},{"id":"recASSvFAFNVJ4ruQ","ref":"1Chr.1.36","text":"The sons of Eliphaz; Teman, and Omar, Zephi, and Gatam, Kenaz, and Timna, and Amalek.","year":-1853}],"allRefs":["Gen.36.11","Gen.36.15","1Chr.1.36"]}
