{"entity":{"id":"recvPCKCYI2cgqgMB","type":"person","slug":"maaseiah_1858","label":"Maaseiah","subtitle":"Male","count":1,"years":"Unknown - Unknown","description":"","rawId":"recvPCKCYI2cgqgMB"},"stats":{"verses":1,"events":0,"family":2},"nodes":[{"id":"recvPCKCYI2cgqgMB","type":"person","group":"focus","label":"Maaseiah","slug":"maaseiah_1858","score":1,"description":""},{"id":"recqlfz4MlN0aLTw4","type":"person","group":"father","label":"Ananiah","slug":"ananiah_257","score":1,"description":""},{"id":"recWjmN4hcgfLxEig","type":"person","group":"children","label":"Azariah","slug":"azariah_542","score":2,"description":""}],"links":[{"source":"recvPCKCYI2cgqgMB","target":"recqlfz4MlN0aLTw4","label":"father"},{"source":"recvPCKCYI2cgqgMB","target":"recWjmN4hcgfLxEig","label":"children"}],"verses":[{"id":"rec9gvBC7Utsp5ddd","ref":"Neh.3.23","text":"After him repaired Benjamin and Hashub over against their house. After him repaired Azariah the son of Maaseiah the son of Ananiah by his house.","year":-445}],"allRefs":["Neh.3.23"]}
