{"entity":{"id":"recJMzF7YDbFpDbZ2","type":"person","slug":"pashur_2283","label":"Pashur","subtitle":"Male","count":5,"years":"Unknown - Unknown","description":"","rawId":"recJMzF7YDbFpDbZ2"},"stats":{"verses":5,"events":0,"family":2},"nodes":[{"id":"recJMzF7YDbFpDbZ2","type":"person","group":"focus","label":"Pashur","slug":"pashur_2283","score":5,"description":""},{"id":"recsw6JO3D6YO4NfQ","type":"person","group":"father","label":"Malchijah","slug":"malchijah_1909","score":2,"description":""},{"id":"recTjcPHCNA0zYYFc","type":"person","group":"children","label":"Zechariah","slug":"zechariah_3024","score":1,"description":"Neh. 11:12."}],"links":[{"source":"recJMzF7YDbFpDbZ2","target":"recsw6JO3D6YO4NfQ","label":"father"},{"source":"recJMzF7YDbFpDbZ2","target":"recTjcPHCNA0zYYFc","label":"children"}],"verses":[{"id":"rec5LWWA6KykSqDMr","ref":"1Chr.9.12","text":"And Adaiah the son of Jeroham, the son of Pashur, the son of Malchijah, and Maasiai the son of Adiel, the son of Jahzerah, the son of Meshullam, the son of Meshillemith, the son of Immer;","year":-536},{"id":"rec7PcWILahJgtnPg","ref":"Ezra.2.38","text":"The children of Pashur, a thousand two hundred forty and seven."},{"id":"recBDPOWkjdiDP48Y","ref":"Ezra.10.22","text":"And of the sons of Pashur; Elioenai, Maaseiah, Ishmael, Nethaneel, Jozabad, and Elasah.","year":-456},{"id":"recjLdWQKD4CHw1VD","ref":"Neh.7.41","text":"The children of Pashur, a thousand two hundred forty and seven.","year":-445},{"id":"recvX4MrhPvHU8zEH","ref":"Neh.11.12","text":"And their brethren that did the work of the house were eight hundred twenty and two: and Adaiah the son of Jeroham, the son of Pelaliah, the son of Amzi, the son of Zechariah, the son of Pashur, the son of Malchiah,","year":-445}],"allRefs":["1Chr.9.12","Ezra.2.38","Ezra.10.22","Neh.7.41","Neh.11.12"]}
