{"entity":{"id":"recBrJHsa3lWJqOc7","type":"person","slug":"prochorus_2371","label":"Prochorus","subtitle":"Male","count":1,"years":"Unknown - Unknown","description":"","rawId":"recBrJHsa3lWJqOc7"},"stats":{"verses":1,"events":21,"family":0},"nodes":[{"id":"recBrJHsa3lWJqOc7","type":"person","group":"focus","label":"Prochorus","slug":"prochorus_2371","score":1,"description":""}],"links":[{"source":"recBrJHsa3lWJqOc7","target":"S","label":"participated"},{"source":"recBrJHsa3lWJqOc7","target":"e","label":"participated"},{"source":"recBrJHsa3lWJqOc7","target":"v","label":"participated"},{"source":"recBrJHsa3lWJqOc7","target":"e","label":"participated"},{"source":"recBrJHsa3lWJqOc7","target":"n","label":"participated"},{"source":"recBrJHsa3lWJqOc7","target":" ","label":"participated"},{"source":"recBrJHsa3lWJqOc7","target":"c","label":"participated"},{"source":"recBrJHsa3lWJqOc7","target":"h","label":"participated"},{"source":"recBrJHsa3lWJqOc7","target":"o","label":"participated"},{"source":"recBrJHsa3lWJqOc7","target":"s","label":"participated"},{"source":"recBrJHsa3lWJqOc7","target":"e","label":"participated"},{"source":"recBrJHsa3lWJqOc7","target":"n","label":"participated"},{"source":"recBrJHsa3lWJqOc7","target":" ","label":"participated"},{"source":"recBrJHsa3lWJqOc7","target":"t","label":"participated"}],"verses":[{"id":"recZOy2rMLOs1xrOW","ref":"Acts.6.5","text":"And the saying pleased the whole multitude: and they chose Stephen, a man full of faith and of the Holy Ghost, and Philip, and Prochorus, and Nicanor, and Timon, and Parmenas, and Nicolas a proselyte of Antioch:","year":33}],"allRefs":["Acts.6.5"]}
