{"entity":{"id":"recvlU77MyXb5w1pu","type":"person","slug":"shaul_2563","label":"Shaul","subtitle":"Male","count":2,"years":"Unknown - Unknown","description":"","rawId":"recvlU77MyXb5w1pu"},"stats":{"verses":2,"events":0,"family":2},"nodes":[{"id":"recvlU77MyXb5w1pu","type":"person","group":"focus","label":"Shaul","slug":"shaul_2563","score":2,"description":""},{"id":"recOUKNJKdvoZk8rD","type":"person","group":"father","label":"Azariah","slug":"azariah_2925","score":2,"description":""},{"id":"recvyuV3CvSco43mt","type":"person","group":"children","label":"Elkanah","slug":"elkanah_1169","score":2,"description":""}],"links":[{"source":"recvlU77MyXb5w1pu","target":"recOUKNJKdvoZk8rD","label":"father"},{"source":"recvlU77MyXb5w1pu","target":"recvyuV3CvSco43mt","label":"children"}],"verses":[{"id":"reci4OMh6TcujDz4Q","ref":"1Chr.6.24","text":"Tahath his son, Uriel his son, Uzziah his son, and Shaul his son.","year":-1700},{"id":"recNl8M2rjS1qCPPW","ref":"1Chr.6.36","text":"The son of Elkanah, the son of Joel, the son of Azariah, the son of Zephaniah,","year":-1042}],"allRefs":["1Chr.6.24","1Chr.6.36"]}
