{"entity":{"id":"recpQW1e4vKiQxpfB","type":"person","slug":"shelomith_2607","label":"Shelomith","subtitle":"Female","count":1,"years":"Unknown - Unknown","description":"","rawId":"recpQW1e4vKiQxpfB"},"stats":{"verses":1,"events":0,"family":2},"nodes":[{"id":"recpQW1e4vKiQxpfB","type":"person","group":"focus","label":"Shelomith","slug":"shelomith_2607","score":1,"description":""},{"id":"recjh4a0CwAhpeU3X","type":"person","group":"siblings","label":"Haran (son of Shimei)","slug":"haran_1409","score":1,"description":""},{"id":"rec9Ylmu7FY7allym","type":"person","group":"siblings","label":"Haziel","slug":"haziel_1467","score":1,"description":""}],"links":[{"source":"recpQW1e4vKiQxpfB","target":"recjh4a0CwAhpeU3X","label":"siblings"},{"source":"recpQW1e4vKiQxpfB","target":"rec9Ylmu7FY7allym","label":"siblings"}],"verses":[{"id":"recS5DIUZxyFHSJ3B","ref":"1Chr.23.9","text":"The sons of Shimei; Shelomith, and Haziel, and Haran, three. These were the chief of the fathers of Laadan.","year":-1015}],"allRefs":["1Chr.23.9"]}
