{"entity":{"id":"recayrHuJYw2vrjFs","type":"person","slug":"syntyche_2806","label":"Syntyche","subtitle":"Female","count":1,"years":"Unknown - Unknown","description":"Fortunate; affable, a female member of the church at Philippi, whom Paul beseeches to be of one mind with Euodias (Phil. 4:2, 3).","rawId":"recayrHuJYw2vrjFs"},"stats":{"verses":1,"events":0,"family":0},"nodes":[{"id":"recayrHuJYw2vrjFs","type":"person","group":"focus","label":"Syntyche","slug":"syntyche_2806","score":1,"description":"Fortunate; affable, a female member of the church at Philippi, whom Paul beseeches to be of one mind with Euodias (Phil. 4:2, 3)."}],"links":[],"verses":[{"id":"recUTbqRSeMkR7R5i","ref":"Phil.4.2","text":"I beseech Euodias, and beseech Syntyche, that they be of the same mind in the Lord.","year":64}],"allRefs":["Phil.4.2"]}
