{"entity":{"id":"recxgTL5Uo15vpF8Y","type":"person","slug":"uthai_2906","label":"Uthai","subtitle":"Male","count":1,"years":"Unknown - Unknown","description":"","rawId":"recxgTL5Uo15vpF8Y"},"stats":{"verses":1,"events":0,"family":1},"nodes":[{"id":"recxgTL5Uo15vpF8Y","type":"person","group":"focus","label":"Uthai","slug":"uthai_2906","score":1,"description":""},{"id":"recedrJfKjuOE8wIl","type":"person","group":"father","label":"Ammihud","slug":"ammihud_227","score":1,"description":"The son of Omri, and the father of Uthai (1 Chr. 9:4)."}],"links":[{"source":"recxgTL5Uo15vpF8Y","target":"recedrJfKjuOE8wIl","label":"father"}],"verses":[{"id":"recDZRbBoG2dkmylK","ref":"1Chr.9.4","text":"Uthai the son of Ammihud, the son of Omri, the son of Imri, the son of Bani, of the children of Pharez the son of Judah.","year":-536}],"allRefs":["1Chr.9.4"]}
