{"entity":{"id":"recj8hRR5z4586l9i","type":"person","slug":"uzzi_2921","label":"Uzzi","subtitle":"Male","count":1,"years":"Unknown - Unknown","description":"A son of Bani. He had the oversight of the Levites after the return from captivity (Neh. 11:22).","rawId":"recj8hRR5z4586l9i"},"stats":{"verses":1,"events":0,"family":1},"nodes":[{"id":"recj8hRR5z4586l9i","type":"person","group":"focus","label":"Uzzi","slug":"uzzi_2921","score":1,"description":"A son of Bani. He had the oversight of the Levites after the return from captivity (Neh. 11:22)."},{"id":"recIE5oyCaJp326Yn","type":"person","group":"father","label":"Bani","slug":"bani_398","score":1,"description":""}],"links":[{"source":"recj8hRR5z4586l9i","target":"recIE5oyCaJp326Yn","label":"father"}],"verses":[{"id":"recNalYaKsZ2GrvhN","ref":"Neh.11.22","text":"The overseer also of the Levites at Jerusalem was Uzzi the son of Bani, the son of Hashabiah, the son of Mattaniah, the son of Micha. Of the sons of Asaph, the singers were over the business of the house of God.","year":-445}],"allRefs":["Neh.11.22"]}
