{"entity":{"id":"rec18ALrKRV4whrgb","type":"person","slug":"zibeon_3062","label":"Zibeon","subtitle":"Male","count":5,"years":"Unknown - Unknown","description":"","rawId":"rec18ALrKRV4whrgb"},"stats":{"verses":5,"events":0,"family":10},"nodes":[{"id":"rec18ALrKRV4whrgb","type":"person","group":"focus","label":"Zibeon","slug":"zibeon_3062","score":5,"description":""},{"id":"recOX7bzog0NALtK7","type":"person","group":"father","label":"Seir","slug":"seir_2485","score":4,"description":"A Horite; one of the “dukes” of Edom (Gen. 36:20-30)."},{"id":"recVAJtqZaVmlvha3","type":"person","group":"children","label":"Ajah","slug":"ajah_178","score":2,"description":""},{"id":"recwl616Y2Hx55XsA","type":"person","group":"children","label":"Anah","slug":"anah_249","score":2,"description":""},{"id":"recZwlJk5ecgPZaeX","type":"person","group":"siblings","label":"Anah","slug":"anah_248","score":5,"description":""},{"id":"recSiSW57dddI3uh2","type":"person","group":"siblings","label":"Dishan","slug":"dishan_1015","score":5,"description":"Antelope, the youngest son of Seir the Horite, head of one of the tribes of Idumaea (Gen. 36:21, 28, 30)."},{"id":"recSb23V3EQtfldTc","type":"person","group":"siblings","label":"Dishon","slug":"dishon_1016","score":4,"description":""},{"id":"recl1WPeQDwuZjXx4","type":"person","group":"siblings","label":"Ezer","slug":"ezer_1238","score":5,"description":"One of the sons of Seir, the native princes, “dukes,” of Mount Hor (Gen. 36:21, 27)."},{"id":"recDVPMfLcfConM50","type":"person","group":"siblings","label":"Lotan","slug":"lotan_1831","score":5,"description":"Coverer, one of the sons of Seir, the Horite (Gen. 36:20, 29)."},{"id":"reclK7fHzOIxFQf6F","type":"person","group":"siblings","label":"Shobal","slug":"shobal_2719","score":5,"description":"The second son of Seir the Horite; one of the Horite “dukes” (Gen. 36:20)."},{"id":"recxozyu7lEjszRf6","type":"person","group":"siblings","label":"Timna","slug":"timna_2860","score":3,"description":""}],"links":[{"source":"rec18ALrKRV4whrgb","target":"recOX7bzog0NALtK7","label":"father"},{"source":"rec18ALrKRV4whrgb","target":"recVAJtqZaVmlvha3","label":"children"},{"source":"rec18ALrKRV4whrgb","target":"recwl616Y2Hx55XsA","label":"children"},{"source":"rec18ALrKRV4whrgb","target":"recZwlJk5ecgPZaeX","label":"siblings"},{"source":"rec18ALrKRV4whrgb","target":"recSiSW57dddI3uh2","label":"siblings"},{"source":"rec18ALrKRV4whrgb","target":"recSb23V3EQtfldTc","label":"siblings"},{"source":"rec18ALrKRV4whrgb","target":"recl1WPeQDwuZjXx4","label":"siblings"},{"source":"rec18ALrKRV4whrgb","target":"recDVPMfLcfConM50","label":"siblings"},{"source":"rec18ALrKRV4whrgb","target":"reclK7fHzOIxFQf6F","label":"siblings"},{"source":"rec18ALrKRV4whrgb","target":"recxozyu7lEjszRf6","label":"siblings"}],"verses":[{"id":"reckdDgj7yX95wCU9","ref":"Gen.36.20","text":"These are the sons of Seir the Horite, who inhabited the land; Lotan, and Shobal, and Zibeon, and Anah,","year":-1806},{"id":"reclCXHQzWWzcs4nJ","ref":"Gen.36.24","text":"And these are the children of Zibeon; both Ajah, and Anah: this was that Anah that found the mules in the wilderness, as he fed the asses of Zibeon his father.","year":-1756},{"id":"recjkLOyYsKJX6bTN","ref":"Gen.36.29","text":"These are the dukes that came of the Horites; duke Lotan, duke Shobal, duke Zibeon, duke Anah,","year":-1756},{"id":"rec0WHSsCUMHiMsiG","ref":"1Chr.1.38","text":"And the sons of Seir; Lotan, and Shobal, and Zibeon, and Anah, and Dishon, and Ezer, and Dishan.","year":-1853},{"id":"recRODu9Qady5JNLU","ref":"1Chr.1.40","text":"The sons of Shobal; Alian, and Manahath, and Ebal, Shephi, and Onam. And the sons of Zibeon; Aiah, and Anah.","year":-1853}],"allRefs":["Gen.36.20","Gen.36.24","Gen.36.29","1Chr.1.38","1Chr.1.40"]}
